{
  "slug": "steamed-fish-with-ginger-scallion",
  "title": "Steamed Fish with Ginger-Scallion",
  "description": "Tender white fish fillets are gently steamed and finished with an aromatic hot oil infused ginger-scallion sauce. Bright, savory, and clean-flavored — this quick method preserves delicate texture and showcases ginger and scallion freshness.",
  "courses": [
    "lunch",
    "dinner"
  ],
  "cuisines": [
    "chinese"
  ],
  "diets_supported": [
    "pescatarian",
    "low-carb",
    "paleo",
    "mediterranean"
  ],
  "primary_ingredient": "cod",
  "ingredient_tags": [
    "cod",
    "fish",
    "ginger",
    "scallion",
    "soy sauce",
    "vegetable oil",
    "sesame oil",
    "salt",
    "sugar",
    "chili",
    "cilantro",
    "lemons"
  ],
  "spice_level": 1,
  "time_total_min": 25,
  "servings_default": 4,
  "servings_min": 1,
  "servings_max": 8,
  "cost_per_serving": "$$",
  "allergens_present": [
    "seafood",
    "soy",
    "sesame"
  ],
  "search_keywords": [
    "steamed fish",
    "ginger scallion",
    "chinese steamed fish",
    "healthy pescatarian",
    "low-carb fish",
    "quick dinner",
    "white fish recipe",
    "cod with ginger",
    "scallion sauce",
    "asian fish",
    "steam cooking",
    "gentle steaming",
    "ginger oil",
    "soy sauce",
    "sesame oil",
    "weeknight meal",
    "light and healthy",
    "cilantro garnish",
    "gluten note soy",
    "simple seafood"
  ],
  "ingredients_json": {
    "servings": 4,
    "ingredients": [
      {
        "display_name": "cod fillets, skin removed",
        "quantity": 600,
        "unit": "g",
        "grams": 600,
        "ml": null,
        "optional": false,
        "notes": "about 4 fillets, ~150 g each"
      },
      {
        "display_name": "fresh ginger, julienned",
        "quantity": 40,
        "unit": "g",
        "grams": 40,
        "ml": null,
        "optional": false,
        "notes": "peeled and cut into thin matchsticks"
      },
      {
        "display_name": "scallions (green onions), julienned",
        "quantity": 60,
        "unit": "g",
        "grams": 60,
        "ml": null,
        "optional": false,
        "notes": "white and green parts separated (reserve whites for steaming under fish if desired)"
      },
      {
        "display_name": "light soy sauce",
        "quantity": 45,
        "unit": "ml",
        "grams": null,
        "ml": 45,
        "optional": false,
        "notes": "about 3 tbsp"
      },
      {
        "display_name": "vegetable oil or neutral oil",
        "quantity": 45,
        "unit": "ml",
        "grams": null,
        "ml": 45,
        "optional": false,
        "notes": "about 3 tbsp, for hot oil finish"
      },
      {
        "display_name": "sesame oil",
        "quantity": 5,
        "unit": "ml",
        "grams": null,
        "ml": 5,
        "optional": false,
        "notes": "about 1 tsp, toasted sesame oil for flavor"
      },
      {
        "display_name": "water (for steaming)",
        "quantity": 500,
        "unit": "ml",
        "grams": null,
        "ml": 500,
        "optional": false,
        "notes": "enough to create steam in wok/steamer"
      },
      {
        "display_name": "kosher salt",
        "quantity": 3,
        "unit": "g",
        "grams": 3,
        "ml": null,
        "optional": false,
        "notes": "about 1/2 tsp, for seasoning fish"
      },
      {
        "display_name": "granulated sugar",
        "quantity": 2,
        "unit": "g",
        "grams": 2,
        "ml": null,
        "optional": false,
        "notes": "about 1/2 tsp, balances soy"
      },
      {
        "display_name": "fresh cilantro leaves",
        "quantity": 8,
        "unit": "g",
        "grams": 8,
        "ml": null,
        "optional": true,
        "notes": "small handful for garnish"
      },
      {
        "display_name": "fresh red chili, thin sliced",
        "quantity": 6,
        "unit": "g",
        "grams": 6,
        "ml": null,
        "optional": true,
        "notes": "optional, for garnish or slight heat"
      },
      {
        "display_name": "lemon or lime wedges",
        "quantity": 1,
        "unit": "each",
        "grams": null,
        "ml": null,
        "optional": true,
        "notes": "for serving"
      }
    ]
  },
  "instructions_json": {
    "time_total_min": 25,
    "steps": [
      {
        "step_no": 1,
        "text": "Prepare fish: pat fillets dry and season both sides lightly with salt. Arrange fillets in a single layer on a heatproof shallow plate that fits your steamer, leaving small gaps between pieces.",
        "time_min": 5
      },
      {
        "step_no": 2,
        "text": "Prepare aromatics: place half the julienned ginger under and around the fillets for gentle infusion and scatter the white parts of scallions under the fish if using; reserve green scallion tops and remaining ginger for sauce.",
        "time_min": 3
      },
      {
        "step_no": 3,
        "text": "Set up steamer: bring water to a vigorous simmer in a wok or large pot with a steamer rack or bamboo steamer; water level should not touch the plate when inserted.",
        "time_min": 5
      },
      {
        "step_no": 4,
        "text": "Steam fish: place the plate with fish into the steamer, cover, and steam until just cooked through and opaque in the center (test thickest part), about 6–7 minutes for 150 g fillets; adjust time for thinner or thicker pieces.",
        "time_min": 7
      },
      {
        "step_no": 5,
        "text": "While fish steams, make sauce: combine light soy sauce and sugar in a small heatproof bowl placed near the stove. Add the reserved julienned ginger and scallion greens to the bowl.",
        "time_min": 2
      },
      {
        "step_no": 6,
        "text": "Heat oil: in a small saucepan or skillet, heat the vegetable oil until shimmering and just smoking; remove from heat and carefully pour the hot oil over the ginger and scallion mixture to release aroma. Stir in sesame oil and taste, adjust salt if needed.",
        "time_min": 1
      },
      {
        "step_no": 7,
        "text": "Finish and serve: remove steamed fish from steamer, pour sauce evenly over the hot fish so flavors permeate, garnish with cilantro and sliced red chili if using, and serve immediately with lemon/lime wedges on the side.",
        "time_min": 2
      }
    ]
  },
  "image_url": null
}